dsl.cpython-39-aarch64-linux-gnu.so
dsl2html-0.2.0.dist-info/METADATA
dsl2html-0.2.0.dist-info/WHEEL
dsl2html-0.2.0.dist-info/top_level.txt
dsl2html-0.2.0.dist-info/RECORD
dsl2html-0.2.0.dist-info/licenses/LICENSE.txt
