Metadata-Version: 2.1
Name: dsl2html
Version: 0.2.0
Summary: DSL to HTML conversion
Author-email: Yi Xing <blandilyte@gmail.com>
Project-URL: Homepage, https://github.com/Crissium/python-dsl
Classifier: Programming Language :: C++
Classifier: License :: OSI Approved :: GNU General Public License v3 (GPLv3)
Classifier: Operating System :: OS Independent
Requires-Python: >=3.0
License-File: LICENSE.txt
